nb_api/__init__.py
nb_api/contrib/__init__.py
nb_api/contrib/fastapi_helpers.py
nb_api/core/__init__.py
nb_api/core/aio_sqlmodel.py
nb_api/core/base.py
nb_api/core/mem.py
nb_api/core/sqlalchemy.py
nb_api/core/sqlmodel.py
nb_api/core/tortoise.py
nb_api/core/types.py
nb_api/core/utils.py
very_nb_api-0.7.dist-info/METADATA
very_nb_api-0.7.dist-info/WHEEL
very_nb_api-0.7.dist-info/top_level.txt
very_nb_api-0.7.dist-info/RECORD
