Metadata-Version: 2.4
Name: very_nb_api
Version: 0.7
Summary: 基于 FastAPI + Pydantic v2 + SQLModel 的自动 CRUD 路由生成框架
Home-page: https://github.com/your-username/nb_api
Author: NB API Team
Author-email: ydf0509@example.com
Keywords: fastapi crud rest api sqlmodel pydantic router
Classifier: Development Status :: 4 - Beta
Classifier: Intended Audience :: Developers
Classifier: Programming Language :: Python :: 3
Classifier: Framework :: FastAPI
Classifier: Topic :: Internet :: WWW/HTTP
Classifier: Topic :: Software Development :: Libraries :: Application Frameworks
Classifier: Topic :: Software Development :: Code Generators
Classifier: Typing :: Typed
Requires-Python: >=3.9
Requires-Dist: fastapi>=0.110.0
Requires-Dist: pydantic>=2.0.0
Provides-Extra: sqlmodel
Requires-Dist: sqlmodel>=0.0.14; extra == "sqlmodel"
Provides-Extra: dev
Requires-Dist: pytest>=7.4.0; extra == "dev"
Requires-Dist: httpx>=0.26.0; extra == "dev"
Requires-Dist: uvicorn[standard]>=0.27.0; extra == "dev"
Dynamic: author
Dynamic: author-email
Dynamic: classifier
Dynamic: description
Dynamic: description-content-type
Dynamic: home-page
Dynamic: keywords
Dynamic: provides-extra
Dynamic: requires-dist
Dynamic: requires-python
Dynamic: summary
